onicalc/__init__.py
onicalc/food.py
onicalc/onicalc.py
onicalc-1.0.dist-info/LICENSE
onicalc-1.0.dist-info/METADATA
onicalc-1.0.dist-info/WHEEL
onicalc-1.0.dist-info/top_level.txt
onicalc-1.0.dist-info/RECORD
