Metadata-Version: 2.1
Name: onicalc
Version: 1.0
Summary: Python Library of various calculators for ONI
Home-page: https://github.com/petebuffon/oni
Author: Pete Buffon
Author-email: pabuffon@gmail.com
License: UNKNOWN
Project-URL: Bug Tracker, https://github.com/petebuffon/oni/issues
Platform: UNKNOWN
Classifier: Programming Language :: Python :: 3
Classifier: License :: OSI Approved :: MIT License
Classifier: Operating System :: OS Independent
License-File: LICENSE
